fastapi_crud_toolkit/__init__.py
fastapi_crud_toolkit/openapi_responses.py
fastapi_crud_toolkit/utils.py
fastapi_crud_toolkit/crud/__init__.py
fastapi_crud_toolkit/crud/mock.py
fastapi_crud_toolkit/crud/model.py
fastapi_crud_toolkit/crud/permission.py
fastapi_crud_toolkit/crud/template.py
fastapi_crud_toolkit-0.0.1.dist-info/METADATA
fastapi_crud_toolkit-0.0.1.dist-info/WHEEL
fastapi_crud_toolkit-0.0.1.dist-info/licenses/LICENSE
fastapi_crud_toolkit-0.0.1.dist-info/RECORD
